mjpl/__init__.py
mjpl/utils.py
mjpl/visualization.py
mjpl/constraint/__init__.py
mjpl/constraint/collision_constraint.py
mjpl/constraint/constraint_interface.py
mjpl/constraint/joint_limit_constraint.py
mjpl/constraint/pose_constraint.py
mjpl/constraint/utils.py
mjpl/inverse_kinematics/__init__.py
mjpl/inverse_kinematics/ik_solver_interface.py
mjpl/inverse_kinematics/mink_ik_solver.py
mjpl/planning/__init__.py
mjpl/planning/cartesian_planner.py
mjpl/planning/rrt.py
mjpl/planning/tree.py
mjpl/planning/utils.py
mjpl/trajectory/__init__.py
mjpl/trajectory/ruckig_trajectory.py
mjpl/trajectory/toppra_trajectory.py
mjpl/trajectory/trajectory_interface.py
mjpl/trajectory/utils.py
mjpl-0.0.1.dist-info/METADATA
mjpl-0.0.1.dist-info/WHEEL
mjpl-0.0.1.dist-info/licenses/LICENSE
mjpl-0.0.1.dist-info/RECORD
