Metadata-Version: 2.4
Name: mjpl
Version: 0.0.1
Summary: MuJoCo motion planning library.
Project-URL: Homepage, https://github.com/adlarkin/mjpl
Author: Ashton Larkin
Maintainer: Ashton Larkin
License: MIT License
License-File: LICENSE
Keywords: manipulation,motion,mujoco,planning,robotics
Classifier: Development Status :: 2 - Pre-Alpha
Classifier: Framework :: Robot Framework :: Library
Classifier: Intended Audience :: Developers
Classifier: Intended Audience :: Science/Research
Classifier: License :: OSI Approved :: MIT License
Classifier: Operating System :: OS Independent
Classifier: Programming Language :: Python :: 3
Classifier: Topic :: Scientific/Engineering
Requires-Python: >=3.10
Requires-Dist: mink>=0.0.8
Requires-Dist: mujoco>=3
Requires-Dist: numpy
Requires-Dist: ruckig
Requires-Dist: toppra>=0.6.3
Provides-Extra: dev
Requires-Dist: coveralls; extra == 'dev'
Requires-Dist: pre-commit; extra == 'dev'
Requires-Dist: robot-descriptions; extra == 'dev'
Requires-Dist: ruff; extra == 'dev'
Requires-Dist: scipy; extra == 'dev'
Provides-Extra: test
Requires-Dist: coveralls; extra == 'test'
Requires-Dist: robot-descriptions; extra == 'test'
Requires-Dist: scipy; extra == 'test'
